odoo/addons/partner_company_default/README.rst
odoo/addons/partner_company_default/__init__.py
odoo/addons/partner_company_default/__manifest__.py
odoo/addons/partner_company_default/i18n/it.po
odoo/addons/partner_company_default/i18n/partner_company_default.pot
odoo/addons/partner_company_default/models/__init__.py
odoo/addons/partner_company_default/models/res_company.py
odoo/addons/partner_company_default/models/res_partner.py
odoo/addons/partner_company_default/readme/CONTEXT.md
odoo/addons/partner_company_default/readme/DESCRIPTION.md
odoo/addons/partner_company_default/static/description/icon.png
odoo/addons/partner_company_default/static/description/index.html
odoo/addons/partner_company_default/tests/__init__.py
odoo/addons/partner_company_default/tests/test_partner_company_default.py
odoo_addon_partner_company_default-17.0.1.0.0.2.dist-info/METADATA
odoo_addon_partner_company_default-17.0.1.0.0.2.dist-info/WHEEL
odoo_addon_partner_company_default-17.0.1.0.0.2.dist-info/top_level.txt
odoo_addon_partner_company_default-17.0.1.0.0.2.dist-info/RECORD
